{
  "labels": [
    "05/26 14:21",
    "06/29 09:01",
    "08/03 12:01",
    "09/08 21:02",
    "10/18 21:03",
    "11/24 18:03",
    "12/30 06:03",
    "03/05 12:25"
  ],
  "datasets": [
    {
      "label": "Copilot Total",
      "type": "bar",
      "data": [
        8729,
        20264,
        70685,
        166582,
        324167,
        535030,
        769798,
        1309814
      ],
      "backgroundColor": "#93c5fd",
      "borderColor": "#93c5fd",
      "borderWidth": 1,
      "yAxisID": "y",
      "order": 2
    },
    {
      "label": "Copilot Merged",
      "type": "bar",
      "data": [
        1594,
        12156,
        41580,
        102423,
        204390,
        346757,
        512100,
        902968
      ],
      "backgroundColor": "#2563eb",
      "borderColor": "#2563eb",
      "borderWidth": 1,
      "yAxisID": "y",
      "order": 2
    },
    {
      "label": "Copilot Success % (Ready)",
      "type": "line",
      "data": [
        75.94092424964268,
        92.44809491216061,
        92.2319329222306,
        92.66198635713899,
        93.12338541025956,
        94.05263043690532,
        94.91805648745732,
        95.47104418150502
      ],
      "borderColor": "#1d4ed8",
      "backgroundColor": "rgba(255, 255, 255, 0.8)",
      "borderWidth": 3,
      "pointRadius": 3,
      "pointHoverRadius": 5,
      "fill": false,
      "yAxisID": "y1",
      "order": 1,
      "rateType": "ready"
    },
    {
      "label": "Copilot Success % (All)",
      "type": "line",
      "data": [
        18.260969183182496,
        59.98815633636004,
        58.82436160430077,
        61.48503439747392,
        63.050834909167186,
        64.8107582752369,
        66.52394524277797,
        68.93864319666761
      ],
      "borderColor": "#1d4ed8",
      "backgroundColor": "rgba(255, 255, 255, 0.8)",
      "borderWidth": 3,
      "pointRadius": 3,
      "pointHoverRadius": 5,
      "fill": false,
      "yAxisID": "y1",
      "order": 1,
      "hidden": true,
      "rateType": "total"
    },
    {
      "label": "Codex Total",
      "type": "bar",
      "data": [
        54211,
        534187,
        894792,
        1424264,
        2015098,
        2455630,
        2704216,
        3481436
      ],
      "backgroundColor": "#fca5a5",
      "borderColor": "#fca5a5",
      "borderWidth": 1,
      "yAxisID": "y",
      "order": 2
    },
    {
      "label": "Codex Merged",
      "type": "bar",
      "data": [
        44230,
        461120,
        782919,
        1243205,
        1744733,
        2123154,
        2341189,
        3004632
      ],
      "backgroundColor": "#dc2626",
      "borderColor": "#dc2626",
      "borderWidth": 1,
      "yAxisID": "y",
      "order": 2
    },
    {
      "label": "Codex Success % (Ready)",
      "type": "line",
      "data": [
        85.80352293008458,
        87.34987687061944,
        88.3764481183351,
        88.04025531004818,
        87.28448189607904,
        87.14447489514075,
        87.25140388511323,
        87.02204780282241
      ],
      "borderColor": "#b91c1c",
      "backgroundColor": "rgba(255, 255, 255, 0.8)",
      "borderWidth": 3,
      "pointRadius": 3,
      "pointHoverRadius": 5,
      "fill": false,
      "yAxisID": "y1",
      "order": 1,
      "rateType": "ready"
    },
    {
      "label": "Codex Success % (All)",
      "type": "line",
      "data": [
        81.58860747818709,
        86.32183111906505,
        87.4973178124078,
        87.287539388765,
        86.58303467126662,
        86.46066386222681,
        86.57551763616516,
        86.30438704029028
      ],
      "borderColor": "#b91c1c",
      "backgroundColor": "rgba(255, 255, 255, 0.8)",
      "borderWidth": 3,
      "pointRadius": 3,
      "pointHoverRadius": 5,
      "fill": false,
      "yAxisID": "y1",
      "order": 1,
      "hidden": true,
      "rateType": "total"
    },
    {
      "label": "Cursor Total",
      "type": "bar",
      "data": [
        null,
        2971,
        52844,
        134574,
        202980,
        236588,
        258811,
        296006
      ],
      "backgroundColor": "#c4b5fd",
      "borderColor": "#c4b5fd",
      "borderWidth": 1,
      "yAxisID": "y",
      "order": 2
    },
    {
      "label": "Cursor Merged",
      "type": "bar",
      "data": [
        null,
        2179,
        33118,
        75644,
        110941,
        130396,
        144870,
        169275
      ],
      "backgroundColor": "#7c3aed",
      "borderColor": "#7c3aed",
      "borderWidth": 1,
      "yAxisID": "y",
      "order": 2
    },
    {
      "label": "Cursor Success % (Ready)",
      "type": "line",
      "data": [
        null,
        75.71230020847811,
        76.83277654046027,
        88.40427272514783,
        95.93403837672838,
        95.90056630139001,
        95.90800458123415,
        96.30921359565777
      ],
      "borderColor": "#6d28d9",
      "backgroundColor": "rgba(255, 255, 255, 0.8)",
      "borderWidth": 3,
      "pointRadius": 3,
      "pointHoverRadius": 5,
      "fill": false,
      "yAxisID": "y1",
      "order": 1,
      "rateType": "ready"
    },
    {
      "label": "Cursor Success % (All)",
      "type": "line",
      "data": [
        null,
        73.3423089868731,
        62.67125879948527,
        56.20996626391428,
        54.65612375603508,
        55.11522139753495,
        55.97520970901546,
        57.18634081741586
      ],
      "borderColor": "#6d28d9",
      "backgroundColor": "rgba(255, 255, 255, 0.8)",
      "borderWidth": 3,
      "pointRadius": 3,
      "pointHoverRadius": 5,
      "fill": false,
      "yAxisID": "y1",
      "order": 1,
      "hidden": true,
      "rateType": "total"
    },
    {
      "label": "Devin Total",
      "type": "bar",
      "data": [
        null,
        29352,
        33972,
        39880,
        45888,
        50935,
        56389,
        71140
      ],
      "backgroundColor": "#86efac",
      "borderColor": "#86efac",
      "borderWidth": 1,
      "yAxisID": "y",
      "order": 2
    },
    {
      "label": "Devin Merged",
      "type": "bar",
      "data": [
        null,
        18719,
        21527,
        25040,
        28241,
        30683,
        34512,
        42585
      ],
      "backgroundColor": "#059669",
      "borderColor": "#059669",
      "borderWidth": 1,
      "yAxisID": "y",
      "order": 2
    },
    {
      "label": "Devin Success % (Ready)",
      "type": "line",
      "data": [
        null,
        65.69914361926155,
        65.36803109437629,
        64.84358814998964,
        63.534308211473565,
        62.178045271242425,
        63.080550529144055,
        61.93371049608052
      ],
      "borderColor": "#047857",
      "backgroundColor": "rgba(255, 255, 255, 0.8)",
      "borderWidth": 3,
      "pointRadius": 3,
      "pointHoverRadius": 5,
      "fill": false,
      "yAxisID": "y1",
      "order": 1,
      "rateType": "ready"
    },
    {
      "label": "Devin Success % (All)",
      "type": "line",
      "data": [
        null,
        63.774189152357586,
        63.3668903803132,
        62.78836509528586,
        61.54332287308228,
        60.23952095808384,
        61.203426200145415,
        59.86083778464999
      ],
      "borderColor": "#047857",
      "backgroundColor": "rgba(255, 255, 255, 0.8)",
      "borderWidth": 3,
      "pointRadius": 3,
      "pointHoverRadius": 5,
      "fill": false,
      "yAxisID": "y1",
      "order": 1,
      "hidden": true,
      "rateType": "total"
    },
    {
      "label": "Codegen Total",
      "type": "bar",
      "data": [
        null,
        4203,
        5040,
        6986,
        7889,
        8679,
        8990,
        9829
      ],
      "backgroundColor": "#fed7aa",
      "borderColor": "#fed7aa",
      "borderWidth": 1,
      "yAxisID": "y",
      "order": 2
    },
    {
      "label": "Codegen Merged",
      "type": "bar",
      "data": [
        null,
        1712,
        2218,
        2825,
        2992,
        3535,
        3713,
        4339
      ],
      "backgroundColor": "#d97706",
      "borderColor": "#d97706",
      "borderWidth": 1,
      "yAxisID": "y",
      "order": 2
    },
    {
      "label": "Codegen Success % (Ready)",
      "type": "line",
      "data": [
        null,
        80.98391674550615,
        74.85656429294633,
        61.829722039833655,
        59.79216626698641,
        61.617570158619486,
        61.67774086378738,
        64.0537348686153
      ],
      "borderColor": "#b45309",
      "backgroundColor": "rgba(255, 255, 255, 0.8)",
      "borderWidth": 3,
      "pointRadius": 3,
      "pointHoverRadius": 5,
      "fill": false,
      "yAxisID": "y1",
      "order": 1,
      "rateType": "ready"
    },
    {
      "label": "Codegen Success % (All)",
      "type": "line",
      "data": [
        null,
        40.73280989769212,
        44.007936507936506,
        40.43801889493272,
        37.926226391177586,
        40.73049890540385,
        41.301446051167964,
        44.14487740360158
      ],
      "borderColor": "#b45309",
      "backgroundColor": "rgba(255, 255, 255, 0.8)",
      "borderWidth": 3,
      "pointRadius": 3,
      "pointHoverRadius": 5,
      "fill": false,
      "yAxisID": "y1",
      "order": 1,
      "hidden": true,
      "rateType": "total"
    },
    {
      "label": "Jules Total",
      "type": "bar",
      "data": [
        null,
        null,
        null,
        null,
        47129,
        82728,
        173227,
        295606
      ],
      "backgroundColor": "#bae6fd",
      "borderColor": "#bae6fd",
      "borderWidth": 1,
      "yAxisID": "y",
      "order": 2
    },
    {
      "label": "Jules Merged",
      "type": "bar",
      "data": [
        null,
        null,
        null,
        null,
        35864,
        61351,
        119692,
        187512
      ],
      "backgroundColor": "#0ea5e9",
      "borderColor": "#0ea5e9",
      "borderWidth": 1,
      "yAxisID": "y",
      "order": 2
    },
    {
      "label": "Jules Success % (Ready)",
      "type": "line",
      "data": [
        null,
        null,
        null,
        null,
        96.29211974761714,
        96.0184677987323,
        95.97626493464838,
        93.83998678817542
      ],
      "borderColor": "#0369a1",
      "backgroundColor": "rgba(255, 255, 255, 0.8)",
      "borderWidth": 3,
      "pointRadius": 3,
      "pointHoverRadius": 5,
      "fill": false,
      "yAxisID": "y1",
      "order": 1,
      "rateType": "ready"
    },
    {
      "label": "Jules Success % (All)",
      "type": "line",
      "data": [
        null,
        null,
        null,
        null,
        76.09751957393537,
        74.15989749540664,
        69.09546433292732,
        63.43308322564495
      ],
      "borderColor": "#0369a1",
      "backgroundColor": "rgba(255, 255, 255, 0.8)",
      "borderWidth": 3,
      "pointRadius": 3,
      "pointHoverRadius": 5,
      "fill": false,
      "yAxisID": "y1",
      "order": 1,
      "hidden": true,
      "rateType": "total"
    }
  ]
}