{
  "labels": [
    "05/26 14:21",
    "06/15 06:00",
    "07/07 00:02",
    "07/28 11:38",
    "08/19 06:01",
    "09/10 09:03",
    "10/05 06:03",
    "10/28 12:03"
  ],
  "datasets": [
    {
      "label": "Copilot Total",
      "type": "bar",
      "data": [
        8729,
        15837,
        27586,
        59310,
        103802,
        172064,
        264865,
        364472
      ],
      "backgroundColor": "#93c5fd",
      "borderColor": "#93c5fd",
      "borderWidth": 1,
      "yAxisID": "y",
      "order": 2
    },
    {
      "label": "Copilot Merged",
      "type": "bar",
      "data": [
        1594,
        7993,
        15877,
        34593,
        63804,
        105682,
        164068,
        232066
      ],
      "backgroundColor": "#2563eb",
      "borderColor": "#2563eb",
      "borderWidth": 1,
      "yAxisID": "y",
      "order": 2
    },
    {
      "label": "Copilot Success % (Ready)",
      "type": "line",
      "data": [
        75.94092424964268,
        90.07212080234393,
        92.07794467320072,
        92.14234344618171,
        92.6360415819734,
        92.63281530761611,
        92.89584689862129,
        93.27898965781975
      ],
      "borderColor": "#1d4ed8",
      "backgroundColor": "rgba(255, 255, 255, 0.8)",
      "borderWidth": 3,
      "pointRadius": 3,
      "pointHoverRadius": 5,
      "fill": false,
      "yAxisID": "y1",
      "order": 1,
      "rateType": "ready"
    },
    {
      "label": "Copilot Success % (All)",
      "type": "line",
      "data": [
        18.260969183182496,
        50.470417377028475,
        57.55455665917495,
        58.32574607991907,
        61.46702375676769,
        61.420169239352795,
        61.9440092122402,
        63.67183212976579
      ],
      "borderColor": "#1d4ed8",
      "backgroundColor": "rgba(255, 255, 255, 0.8)",
      "borderWidth": 3,
      "pointRadius": 3,
      "pointHoverRadius": 5,
      "fill": false,
      "yAxisID": "y1",
      "order": 1,
      "hidden": true,
      "rateType": "total"
    },
    {
      "label": "Codex Total",
      "type": "bar",
      "data": [
        54211,
        322513,
        622242,
        837799,
        1118295,
        1445134,
        1805174,
        2170194
      ],
      "backgroundColor": "#fca5a5",
      "borderColor": "#fca5a5",
      "borderWidth": 1,
      "yAxisID": "y",
      "order": 2
    },
    {
      "label": "Codex Merged",
      "type": "bar",
      "data": [
        44230,
        273180,
        538777,
        732132,
        977782,
        1261373,
        1567572,
        1877734
      ],
      "backgroundColor": "#dc2626",
      "borderColor": "#dc2626",
      "borderWidth": 1,
      "yAxisID": "y",
      "order": 2
    },
    {
      "label": "Codex Success % (Ready)",
      "type": "line",
      "data": [
        85.80352293008458,
        87.26680296447739,
        87.58123717842432,
        88.28334326140904,
        88.25169435000049,
        88.03534051785206,
        87.55179560903929,
        87.21229914061887
      ],
      "borderColor": "#b91c1c",
      "backgroundColor": "rgba(255, 255, 255, 0.8)",
      "borderWidth": 3,
      "pointRadius": 3,
      "pointHoverRadius": 5,
      "fill": false,
      "yAxisID": "y1",
      "order": 1,
      "rateType": "ready"
    },
    {
      "label": "Codex Success % (All)",
      "type": "line",
      "data": [
        81.58860747818709,
        84.70356233702208,
        86.586408503444,
        87.38754760986825,
        87.43506856419818,
        87.28415496417632,
        86.83772312253556,
        86.52378543116423
      ],
      "borderColor": "#b91c1c",
      "backgroundColor": "rgba(255, 255, 255, 0.8)",
      "borderWidth": 3,
      "pointRadius": 3,
      "pointHoverRadius": 5,
      "fill": false,
      "yAxisID": "y1",
      "order": 1,
      "hidden": true,
      "rateType": "total"
    },
    {
      "label": "Cursor Total",
      "type": "bar",
      "data": [
        null,
        1169,
        9554,
        37828,
        95522,
        136627,
        169731,
        215438
      ],
      "backgroundColor": "#c4b5fd",
      "borderColor": "#c4b5fd",
      "borderWidth": 1,
      "yAxisID": "y",
      "order": 2
    },
    {
      "label": "Cursor Merged",
      "type": "bar",
      "data": [
        null,
        885,
        7135,
        26235,
        54762,
        76815,
        96319,
        116840
      ],
      "backgroundColor": "#7c3aed",
      "borderColor": "#7c3aed",
      "borderWidth": 1,
      "yAxisID": "y",
      "order": 2
    },
    {
      "label": "Cursor Success % (Ready)",
      "type": "line",
      "data": [
        null,
        79.65796579657966,
        75.7109507640068,
        74.38332860788205,
        82.25857329548015,
        88.70706977388734,
        94.33143663020165,
        96.02708877821063
      ],
      "borderColor": "#6d28d9",
      "backgroundColor": "rgba(255, 255, 255, 0.8)",
      "borderWidth": 3,
      "pointRadius": 3,
      "pointHoverRadius": 5,
      "fill": false,
      "yAxisID": "y1",
      "order": 1,
      "rateType": "ready"
    },
    {
      "label": "Cursor Success % (All)",
      "type": "line",
      "data": [
        null,
        75.70573139435415,
        74.6807619845091,
        69.35338902400339,
        57.3292016498817,
        56.2224157743345,
        56.7480307074135,
        54.23370064705391
      ],
      "borderColor": "#6d28d9",
      "backgroundColor": "rgba(255, 255, 255, 0.8)",
      "borderWidth": 3,
      "pointRadius": 3,
      "pointHoverRadius": 5,
      "fill": false,
      "yAxisID": "y1",
      "order": 1,
      "hidden": true,
      "rateType": "total"
    },
    {
      "label": "Devin Total",
      "type": "bar",
      "data": [
        null,
        28626,
        30201,
        32715,
        37350,
        40103,
        43426,
        47601
      ],
      "backgroundColor": "#86efac",
      "borderColor": "#86efac",
      "borderWidth": 1,
      "yAxisID": "y",
      "order": 2
    },
    {
      "label": "Devin Merged",
      "type": "bar",
      "data": [
        null,
        17465,
        19324,
        20756,
        23623,
        25133,
        26760,
        29161
      ],
      "backgroundColor": "#059669",
      "borderColor": "#059669",
      "borderWidth": 1,
      "yAxisID": "y",
      "order": 2
    },
    {
      "label": "Devin Success % (Ready)",
      "type": "line",
      "data": [
        null,
        66.26826029216467,
        65.94996757789836,
        65.47220995520787,
        65.24428977821968,
        64.70573090983987,
        63.59920144500428,
        63.24087527921755
      ],
      "borderColor": "#047857",
      "backgroundColor": "rgba(255, 255, 255, 0.8)",
      "borderWidth": 3,
      "pointRadius": 3,
      "pointHoverRadius": 5,
      "fill": false,
      "yAxisID": "y1",
      "order": 1,
      "rateType": "ready"
    },
    {
      "label": "Devin Success % (All)",
      "type": "line",
      "data": [
        null,
        61.01096904911619,
        63.98463627032217,
        63.44490294971725,
        63.24765729585007,
        62.67112186120739,
        61.622069727812836,
        61.26131803953698
      ],
      "borderColor": "#047857",
      "backgroundColor": "rgba(255, 255, 255, 0.8)",
      "borderWidth": 3,
      "pointRadius": 3,
      "pointHoverRadius": 5,
      "fill": false,
      "yAxisID": "y1",
      "order": 1,
      "hidden": true,
      "rateType": "total"
    },
    {
      "label": "Codegen Total",
      "type": "bar",
      "data": [
        null,
        4141,
        4176,
        4841,
        5654,
        7012,
        7947,
        8022
      ],
      "backgroundColor": "#fed7aa",
      "borderColor": "#fed7aa",
      "borderWidth": 1,
      "yAxisID": "y",
      "order": 2
    },
    {
      "label": "Codegen Merged",
      "type": "bar",
      "data": [
        null,
        1515,
        1697,
        2090,
        2461,
        2834,
        3102,
        3092
      ],
      "backgroundColor": "#d97706",
      "borderColor": "#d97706",
      "borderWidth": 1,
      "yAxisID": "y",
      "order": 2
    },
    {
      "label": "Codegen Success % (Ready)",
      "type": "line",
      "data": [
        null,
        85.69004524886877,
        79.63397465978413,
        75.80703663402248,
        71.66569598136284,
        61.756373937677054,
        61.21965660153938,
        60.2729044834308
      ],
      "borderColor": "#b45309",
      "backgroundColor": "rgba(255, 255, 255, 0.8)",
      "borderWidth": 3,
      "pointRadius": 3,
      "pointHoverRadius": 5,
      "fill": false,
      "yAxisID": "y1",
      "order": 1,
      "rateType": "ready"
    },
    {
      "label": "Codegen Success % (All)",
      "type": "line",
      "data": [
        null,
        36.58536585365854,
        40.63697318007663,
        43.17289816153687,
        43.526706756278735,
        40.41642897889333,
        39.03359758399396,
        38.544003989030166
      ],
      "borderColor": "#b45309",
      "backgroundColor": "rgba(255, 255, 255, 0.8)",
      "borderWidth": 3,
      "pointRadius": 3,
      "pointHoverRadius": 5,
      "fill": false,
      "yAxisID": "y1",
      "order": 1,
      "hidden": true,
      "rateType": "total"
    },
    {
      "label": "Jules Total",
      "type": "bar",
      "data": [
        null,
        null,
        null,
        null,
        null,
        null,
        36873,
        52432
      ],
      "backgroundColor": "#bae6fd",
      "borderColor": "#bae6fd",
      "borderWidth": 1,
      "yAxisID": "y",
      "order": 2
    },
    {
      "label": "Jules Merged",
      "type": "bar",
      "data": [
        null,
        null,
        null,
        null,
        null,
        null,
        28914,
        40089
      ],
      "backgroundColor": "#0ea5e9",
      "borderColor": "#0ea5e9",
      "borderWidth": 1,
      "yAxisID": "y",
      "order": 2
    },
    {
      "label": "Jules Success % (Ready)",
      "type": "line",
      "data": [
        null,
        null,
        null,
        null,
        null,
        null,
        96.70880995384307,
        96.08599779492833
      ],
      "borderColor": "#0369a1",
      "backgroundColor": "rgba(255, 255, 255, 0.8)",
      "borderWidth": 3,
      "pointRadius": 3,
      "pointHoverRadius": 5,
      "fill": false,
      "yAxisID": "y1",
      "order": 1,
      "rateType": "ready"
    },
    {
      "label": "Jules Success % (All)",
      "type": "line",
      "data": [
        null,
        null,
        null,
        null,
        null,
        null,
        78.41510048002604,
        76.45903265181569
      ],
      "borderColor": "#0369a1",
      "backgroundColor": "rgba(255, 255, 255, 0.8)",
      "borderWidth": 3,
      "pointRadius": 3,
      "pointHoverRadius": 5,
      "fill": false,
      "yAxisID": "y1",
      "order": 1,
      "hidden": true,
      "rateType": "total"
    }
  ]
}